{
  "content_id": "images",
  "datatype": "image-downloads",
  "format": "products:1.0",
  "products": {
    "archlinux:current:arm64:default": {
      "aliases": "archlinux/current/default,archlinux/current,archlinux",
      "arch": "arm64",
      "os": "Archlinux",
      "release": "current",
      "release_title": "current",
      "variant": "default",
      "versions": {
        "20260621_02:49": {
          "items": {
            "root.tar.xz": {
              "ftype": "root.tar.xz",
              "sha256": "0493b37f8060f8d5b2dd1f5a164891d9adf99bce97f1ae0bc438d47a663d88e5",
              "size": 146501864,
              "path": "images/rootfs.tar.xz",
              "combined_sha256": "6e5c69edae5f0001b830d33d1be0fe5b3ef45282d82aebf1f613639572908fba",
              "combined_rootxz_sha256": "6e5c69edae5f0001b830d33d1be0fe5b3ef45282d82aebf1f613639572908fba"
            },
            "incus.tar.xz": {
              "ftype": "incus.tar.xz",
              "sha256": "900f9a150b778d984e67e51e63ecfaeae454f6d37ec5a3ec92450892ba5a823f",
              "size": 532,
              "path": "images/metadata.tar.xz",
              "combined_sha256": "6e5c69edae5f0001b830d33d1be0fe5b3ef45282d82aebf1f613639572908fba",
              "combined_rootxz_sha256": "6e5c69edae5f0001b830d33d1be0fe5b3ef45282d82aebf1f613639572908fba"
            }
          }
        }
      }
    }
  }
}
